{"type": "Feature", "id": 23388264, "properties": {"woe:id": 23388264, "woe:parent_id": 1522006, "woe:name": "An-Nuzhah Airport", "woe:placetype": 14, "woe:placetype_name": "Airport", "woe:lang": "ENG", "iso:country": "EG", "meta:provider": ["geoplanet:7.3.1", "geoplanet:7.3.2", "geoplanet:7.4.0", "geoplanet:7.4.1", "geoplanet:7.5.1", "geoplanet:7.5.2", "geoplanet:7.6.0", "geoplanet:7.8.1", "geoplanet:7.9.0", "geoplanet:7.10.0", "geoplanet:8.0.0", "woeplanet:8.0.0"], "meta:indexed": "2020-08-20T20:26:36.677281", "woe:alias_ENG_V": ["ALY Airport", "ALY", "Alexandria Airport"], "meta:updated": "2020-08-22T02:50:46.581145", "woe:hierarchy": {"continent": 24865670, "country": 23424802, "town": 0, "planet": 1, "county": 0, "suburb": 0, "state": 2345228, "region": 0, "localadmin": 0}, "woe:timezone_id": 28350693, "woe:hash": "stt33sbq8w7e", "woe:centroid": [29.9491, 31.184469], "geom:latitude": 31.184469, "geom:longitude": 29.9491, "geom:hash": "stt33sbq8w7e", "woe:latitude": 31.184469, "geom:centroid": [29.9491, 31.184469], "woe:longitude": 29.9491, "woe:repo": "woeplanet-airport-eg"}, "geometry": {"coordinates": [29.9491, 31.184469], "type": "Point"}}