{"type": "Feature", "id": 12512666, "properties": {"woe:id": 12512666, "woe:parent_id": 1522328, "woe:name": "Aswan Airport", "woe:placetype": 14, "woe:placetype_name": "Airport", "woe:lang": "ENG", "iso:country": "EG", "meta:provider": ["geoplanet:7.3.1", "geoplanet:7.3.2", "geoplanet:7.4.0", "geoplanet:7.4.1", "geoplanet:7.5.1", "geoplanet:7.5.2", "geoplanet:7.6.0", "geoplanet:7.8.1", "geoplanet:7.9.0", "geoplanet:7.10.0", "geoplanet:8.0.0", "woeplanet:8.0.0"], "meta:indexed": "2020-08-20T20:26:36.633681", "woe:alias_ENG_V": ["ASW Airport", "ASW"], "meta:updated": "2020-08-22T02:50:46.563221", "woe:hierarchy": {"continent": 24865670, "country": 23424802, "town": 0, "planet": 1, "county": 0, "suburb": 0, "state": 2345238, "region": 0, "localadmin": 0}, "woe:timezone_id": 28350693, "woe:hash": "ssr26fsn1pf1", "woe:centroid": [32.821701, 23.965], "geom:latitude": 23.965, "geom:longitude": 32.821701, "geom:hash": "ssr26fsn1pf1", "woe:latitude": 23.965, "geom:centroid": [32.821701, 23.965], "woe:longitude": 32.821701, "woe:repo": "woeplanet-airport-eg"}, "geometry": {"coordinates": [32.821701, 23.965], "type": "Point"}}